Metadata-Version: 2.1
Name: django-munigeo-turku
Version: 0.3
Summary: A Django app for processing municipality-related geospatial data.
Home-page: https://github.com/City-of-Turku/django-munigeo
Author: City of Turku
Author-email: sovellustuki@turku.fi
License: BSD License
Platform: UNKNOWN
Classifier: Environment :: Web Environment
Classifier: Framework :: Django
Classifier: Intended Audience :: Developers
Classifier: License :: OSI Approved :: BSD License
Classifier: Operating System :: OS Independent
Classifier: Programming Language :: Python
Classifier: Programming Language :: Python :: 2.6
Classifier: Programming Language :: Python :: 2.7
Classifier: Programming Language :: Python :: 3
Classifier: Programming Language :: Python :: 3.2
Classifier: Programming Language :: Python :: 3.3
Classifier: Programming Language :: Python :: 3.4
Classifier: Programming Language :: Python :: 3.5
Classifier: Programming Language :: Python :: 3.6
Classifier: Programming Language :: Python :: 3.7
Classifier: Programming Language :: Python :: 3.8
Classifier: Topic :: Internet :: WWW/HTTP
Classifier: Topic :: Internet :: WWW/HTTP :: Dynamic Content
Classifier: Topic :: Scientific/Engineering :: GIS
Requires-Dist: Django
Requires-Dist: requests
Requires-Dist: requests-cache
Requires-Dist: django-mptt
Requires-Dist: django-parler
Requires-Dist: django-parler-rest
Requires-Dist: six
Requires-Dist: pyyaml
